{
  "papers": [
    {
      "paper_code": "dh_21_P_22",
      "abstract": "There are a number of risks to interpretability found in the growing use of complicated computational methods within the humanities. Greater attention needs to be given to the format and presentation of the underlying data and the interpretation of any data-derived results. Visually appealing graphic renderings of data, high classification accuracy and confidence scores, and impressive summary statistics can be rhetorically structured to appeal to preconceived notions and commonplace understandings. While making arguments from the summary of significant features might be permissible in some applications of what is now commonly called data science, humanistic uses of computation put forward in the service of academic arguments require much greater access to and grounding in interpretable digital objects. When features are derived from text, these underlying features need to be shown and interpreted. This essay argues that claims made on behalf of computational models need to be evaluated and warranted by a set of shared assumptions and the ability to test and verify that the data are indeed comprehensible according to the norms of the shared interpretative community.",
      "events": [
        {
          "Background/Introduction": "",
          "Text": "There are a number of risks to interpretability found in the growing use of complicated computational methods within the humanities. Greater attention needs to be given to the format and presentation of the underlying data and the interpretation of any data-derived results.",
          "Main Action": "<NONE>",
          "Arguments": {
            "Agent": [
              "Greater attention"
            ],
            "Object": {
              "Primary Object": [
                "attention"
              ],
              "Primary Modifier": [
                "<NONE>"
              ],
              "Secondary Object": [
                "format and presentation of the underlying data and the interpretation of any data-derived results"
              ],
              "Secondary Modifier": [
                "<NONE>"
              ]
            },
            "Context": [
              "risks to interpretability found in the growing use of complicated computational methods within the humanities"
            ],
            "Purpose": [
              "needs to be given"
            ],
            "Method": [
              "<NONE>"
            ],
            "Results": [
              "<NONE>"
            ],
            "Analysis": [
              "<NONE>"
            ],
            "Challenge": [
              "<NONE>"
            ],
            "Ethical": [
              "<NONE>"
            ],
            "Implications": [
              "<NONE>"
            ],
            "Contradictions": [
              "<NONE>"
            ]
          }
        },
        {
          "Conclusions/Implications": "",
          "Text": "Visually appealing graphic renderings of data, high classification accuracy and confidence scores, and impressive summary statistics can be rhetorically structured to appeal to preconceived notions and commonplace understandings. While making arguments from the summary of significant features might be permissible in some applications of what is now commonly called data science, humanistic uses of computation put forward in the service of academic arguments require much greater access to and grounding in interpretable digital objects. When features are derived from text, these underlying features need to be shown and interpreted. This essay argues that claims made on behalf of computational models need to be evaluated and warranted by a set of shared assumptions and the ability to test and verify that the data are indeed comprehensible according to the norms of the shared interpretative community.",
          "Main Action": "<ARGUMENTS>",
          "Arguments": {
            "Agent": [
              "This essay"
            ],
            "Object": {
              "Primary Object": [
                "claims made on behalf of computational models"
              ],
              "Primary Modifier": [
                "<NONE>"
              ],
              "Secondary Object": [
                "shared assumptions",
                "data being comprehensible according to the norms of the shared interpretative community"
              ],
              "Secondary Modifier": [
                "<NONE>"
              ]
            },
            "Context": [
              "humanistic uses of computation",
              "academic arguments"
            ],
            "Purpose": [
              "evaluated and warranted"
            ],
            "Method": [
              "set of shared assumptions",
              "ability to test and verify"
            ],
            "Results": [
              "<NONE>"
            ],
            "Analysis": [
              "<NONE>"
            ],
            "Challenge": [
              "underlying features need to be shown and interpreted"
            ],
            "Ethical": [
              "<NONE>"
            ],
            "Implications": [
              "broader significance or potential for future applications/research"
            ],
            "Contradictions": [
              "making arguments from the summary of significant features might be permissible in some applications but requires more transparency in humanistic contexts"
            ]
          }
        }
      ]
    },
    {
      "paper_code": "dh_21_P_21",
      "abstract": "Katherine Bode theorizes a new approach to “data rich” literary history, in which the researcher constructs a “a scholarly edition of a literary system” pairing annotated data with a critical apparatus. Bode challenges the rhetoric around distant reading, arguing it recapitulates the historical oversights of New Criticism. A World of Fiction comprises a book and paired database which apply this framework to the fiction published in nineteenth-century Australian newspapers. Bode's investigation advances new ideas about the gender of Australian fiction authors, the networks of influence among provincial and metropolitan newspapers, and the national character of fiction in the period. A World of Fiction is an important intervention in conversations about computational literary-historical analysis, as well as around the construction and use of digitized historical archives.",
      "events": [
        {
          "Background/Introduction": "",
          "Text": "Katherine Bode theorizes a new approach to “data rich” literary history, in which the researcher constructs a “a scholarly edition of a literary system” pairing annotated data with a critical apparatus.",
          "Main Action": "theory",
          "Arguments": {
            "Agent": [
              "Katherine Bode"
            ],
            "Object": {
              "Primary Object": [
                "new approach"
              ],
              "Primary Modifier": [
                "<NONE>"
              ],
              "Secondary Object": [
                "literary history"
              ],
              "Secondary Modifier": [
                "<NONE>"
              ]
            },
            "Context": [
              "in which the researcher constructs a 'scholarly edition of a literary system' pairing annotated data with a critical apparatus"
            ],
            "Purpose": [
              "to theorize"
            ],
            "Method": [
              "constructs a 'scholarly edition of a literary system' pairing annotated data with a critical apparatus"
            ],
            "Results": [
              "<NONE>"
            ],
            "Analysis": [
              "<NONE>"
            ],
            "Challenge": [
              "<NONE>"
            ],
            "Ethical": [
              "<NONE>"
            ],
            "Implications": [
              "<NONE>"
            ],
            "Contradictions": [
              "<NONE>"
            ]
          }
        },
        {
          "Methods/Approach": "",
          "Text": "Bode challenges the rhetoric around distant reading, arguing it recapitulates the historical oversights of New Criticism. A World of Fiction comprises a book and paired database which apply this framework to the fiction published in nineteenth-century Australian newspapers. ",
          "Main Action": "<NONE>",
          "Arguments": {
            "Agent": [
              "A World of Fiction"
            ],
            "Object": {
              "Primary Object": [
                "book and paired database"
              ],
              "Primary Modifier": [
                "<NONE>"
              ],
              "Secondary Object": [
                "fiction published in nineteenth-century Australian newspapers"
              ],
              "Secondary Modifier": [
                "<NONE>"
              ]
            },
            "Context": [
              "challenges the rhetoric around distant reading, arguing it recapitulates the historical oversights of New Criticism"
            ],
            "Purpose": [
              "recapitulates the historical oversights of New Criticism"
            ],
            "Method": [
              "apply this framework"
            ],
            "Results": [
              "<NONE>"
            ],
            "Analysis": [
              "arguing it recapitulates the historical oversights of New Criticism"
            ],
            "Challenge": [
              "<NONE>"
            ],
            "Ethical": [
              "<NONE>"
            ],
            "Implications": [
              "<NONE>"
            ],
            "Contradictions": [
              "<NONE>"
            ]
          }
        },
        {
          "Results/Findings": "",
          "Text": "Bode's investigation advances new ideas about the gender of Australian fiction authors, the networks of influence among provincial and metropolitan newspapers, and the national character of fiction in the period.",
          "Main Action": "advances",
          "Arguments": {
            "Agent": [
              "Bode's investigation"
            ],
            "Object": {
              "Primary Object": [
                "new ideas"
              ],
              "Primary Modifier": [
                "<NONE>"
              ],
              "Secondary Object": [
                "networks of influence among provincial and metropolitan newspapers",
                "national character of fiction"
              ],
              "Secondary Modifier": [
                "<NONE>"
              ]
            },
            "Context": [
              "gender of Australian fiction authors"
            ],
            "Purpose": [
              "<NONE>"
            ],
            "Method": [
              "<NONE>"
            ],
            "Results": [
              "<NONE>"
            ],
            "Analysis": [
              "<NONE>"
            ],
            "Challenge": [
              "<NONE>"
            ],
            "Ethical": [
              "<NONE>"
            ],
            "Implications": [
              "<NONE>"
            ],
            "Contradictions": [
              "<NONE>"
            ]
          }
        },
        {
          "Conclusions/Implications": "",
          "Text": "A World of Fiction is an important intervention in conversations about computational literary-historical analysis, as well as around the construction and use of digitized historical archives.",
          "Main Action": "<NONE>",
          "Arguments": {
            "Agent": [
              "An important intervention"
            ],
            "Object": {
              "Primary Object": [
                "conversations about computational literary-historical analysis"
              ],
              "Primary Modifier": [
                "<NONE>"
              ],
              "Secondary Object": [
                "around the construction and use of digitized historical archives"
              ],
              "Secondary Modifier": [
                "<NONE>"
              ]
            },
            "Context": [
              "a World of Fiction"
            ],
            "Purpose": [
              "<NONE>"
            ],
            "Method": [
              "<NONE>"
            ],
            "Results": [
              "<NONE>"
            ],
            "Analysis": [
              "<NONE>"
            ],
            "Challenge": [
              "<NONE>"
            ],
            "Ethical": [
              "<NONE>"
            ],
            "Implications": [
              "<NONE>"
            ],
            "Contradictions": [
              "<NONE>"
            ]
          }
        }
      ]
    }
  ]
}